demo/apps/__init__.py
demo/apps/test/__init__.py
demo/apps/test/management/__init__.py
demo/apps/test/management/commands/__init__.py
demo/apps/test/management/commands/test_command.py
demo/apps/test/management/commands/test_command_error.py
demo/apps/test/management/commands/test_command_error_unicode.py
demo/apps/test/management/commands/test_command_killed.py
demo/apps/test/management/commands/test_command_monitor.py
demo/apps/test/management/commands/test_command_monitor_error.py
demo/apps/test/management/commands/test_command_noargs.py
demo/apps/test/management/commands/test_command_one.py
demo/apps/test/management/commands/test_command_stdout.py
demo/apps/test/management/commands/test_subprocess.py
demo/demo/__init__.py
demo/demo/local_settings.py
demo/demo/settings.py
demo/demo/urls.py
demo/demo/wsgi.py
django_mmc-1.6.5.dist-info/DESCRIPTION.rst
django_mmc-1.6.5.dist-info/METADATA
django_mmc-1.6.5.dist-info/RECORD
django_mmc-1.6.5.dist-info/WHEEL
django_mmc-1.6.5.dist-info/metadata.json
django_mmc-1.6.5.dist-info/top_level.txt
mmc/__init__.py
mmc/admin.py
mmc/defaults.py
mmc/lock.py
mmc/mixins.py
mmc/models.py
mmc/test_cases.py
mmc/utils.py
mmc/management/__init__.py
mmc/management/commands/__init__.py
mmc/management/commands/mmc_cleanup.py
mmc/management/commands/mmc_notify.py
mmc/migrations/0001_initial.py
mmc/migrations/0002_mmclog_was_notified.py
mmc/migrations/0003_mmclog_stdout_messages.py
mmc/migrations/0004_mmcemail_ignore.py
mmc/migrations/0005_auto_20150315_0644.py
mmc/migrations/0006_auto_20150424_2114.py
mmc/migrations/0007_mmcscript_calls.py
mmc/migrations/0008_mmcscript_real_time.py
mmc/migrations/0009_auto_20150425_1540.py
mmc/migrations/0010_mmcscript_enable_queries.py
mmc/migrations/0011_auto_20150425_1710.py
mmc/migrations/0012_auto_20150717_0649.py
mmc/migrations/0013_mmclog_is_fixed.py
mmc/migrations/0014_mmcscript_temporarily_disabled.py
mmc/migrations/0015_auto_20160706_1633.py
mmc/migrations/__init__.py
mmc/south_migrations/0001_initial.py
mmc/south_migrations/0002_auto__add_field_mmcscript_ignore__add_field_mmchost_ignore.py
mmc/south_migrations/0003_auto__add_mmcemail.py
