Metadata-Version: 2.0
Name: django-mmc
Version: 1.6.5
Summary: App for monitoring management commands on Django.
Home-page: https://github.com/LPgenerator/django-mmc
Author: GoTLiuM InSPiRiT
Author-email: gotlium@gmail.com
License: UNKNOWN
Keywords: django management commands monitoring
Platform: UNKNOWN
Classifier: Development Status :: 5 - Production/Stable
Classifier: Environment :: Web Environment
Classifier: Framework :: Django
Classifier: Intended Audience :: Developers
Classifier: License :: OSI Approved :: GNU General Public License (GPL)
Classifier: Operating System :: OS Independent
Classifier: Programming Language :: Python
Classifier: Programming Language :: Python :: 2.6
Classifier: Programming Language :: Python :: 2.7
Classifier: Programming Language :: Python :: 3
Classifier: Programming Language :: Python :: 3.4
